ksqldb_udf/__init__.py
ksqldb_udf/adapter.py
ksqldb_udf/ksqldb-udf-python-core-0.1.0-SNAPSHOT-jar-with-dependencies.jar
ksqldb_udf/mvnw
ksqldb_udf/mvnw.cmd
ksqldb_udf/pom-template.xml
ksqldb_udf/wheel.py
ksqldb_udf/mvn/wrapper/maven-wrapper.properties
ksqldb_udf-1.0.1.dist-info/LICENSE.txt
ksqldb_udf-1.0.1.dist-info/METADATA
ksqldb_udf-1.0.1.dist-info/WHEEL
ksqldb_udf-1.0.1.dist-info/entry_points.txt
ksqldb_udf-1.0.1.dist-info/top_level.txt
ksqldb_udf-1.0.1.dist-info/RECORD
