Metadata-Version: 2.1
Name: ksqldb-udf
Version: 1.0.1
Summary: A library for creating ksqlDB UDFs written in Python
Home-page: https://github.com/confluentinc/csid-ksqldb-udf-python
License: Confluent Community License Agreement
Platform: UNKNOWN
License-File: LICENSE.txt
Requires-Dist: fire (==0.4.*)
Requires-Dist: wheel-inspect (==1.7.*)
Requires-Dist: pyyaml (==5.4.*)
